mygroup/__init__.py
mygroup/math_tools.py
mygroup/text_tools.py
mygroup-0.1.0.dist-info/METADATA
mygroup-0.1.0.dist-info/WHEEL
mygroup-0.1.0.dist-info/top_level.txt
mygroup-0.1.0.dist-info/RECORD
